tifft/__init__.py
tifft/bollingerbands.py
tifft/cli.py
tifft/datareader.py
tifft/macd.py
tifft/rsi.py
tifft-0.1.2.dist-info/LICENSE
tifft-0.1.2.dist-info/METADATA
tifft-0.1.2.dist-info/WHEEL
tifft-0.1.2.dist-info/entry_points.txt
tifft-0.1.2.dist-info/top_level.txt
tifft-0.1.2.dist-info/RECORD
