Metadata-Version: 2.1
Name: tifft
Version: 0.1.2
Summary: Technical Indicators for Financial Trading
Home-page: https://github.com/dceoy/tifft
Author: Daichi Narushima
Author-email: dnarsil+github@gmail.com
Classifier: Development Status :: 4 - Beta
Classifier: Environment :: Console
Classifier: Intended Audience :: Financial and Insurance Industry
Classifier: License :: OSI Approved :: GNU General Public License v3 (GPLv3)
Classifier: Operating System :: POSIX :: Linux
Classifier: Operating System :: MacOS
Classifier: Programming Language :: Python :: 3
Classifier: Topic :: Office/Business :: Financial :: Investment
Requires-Python: >=3.6
License-File: LICENSE
Requires-Dist: docopt
Requires-Dist: pandas
Requires-Dist: pandas-datareader
